pymap/__about__.py
pymap/__init__.py
pymap/concurrent.py
pymap/config.py
pymap/context.py
pymap/exceptions.py
pymap/fetch.py
pymap/filter.py
pymap/flags.py
pymap/frozen.py
pymap/health.py
pymap/listtree.py
pymap/mailbox.py
pymap/main.py
pymap/message.py
pymap/py.typed
pymap/search.py
pymap/selected.py
pymap/service.py
pymap/sockets.py
pymap/threads.py
pymap/user.py
pymap/versioned.py
pymap/admin/__init__.py
pymap/admin/errors.py
pymap/admin/typing.py
pymap/admin/handlers/__init__.py
pymap/admin/handlers/mailbox.py
pymap/admin/handlers/system.py
pymap/admin/handlers/user.py
pymap/backend/__init__.py
pymap/backend/mailbox.py
pymap/backend/session.py
pymap/backend/dict/__init__.py
pymap/backend/dict/filter.py
pymap/backend/dict/mailbox.py
pymap/backend/dict/demo/sieve
pymap/backend/dict/demo/INBOX/message-1.txt
pymap/backend/dict/demo/INBOX/message-2.txt
pymap/backend/dict/demo/INBOX/message-3.txt
pymap/backend/dict/demo/INBOX/message-4.txt
pymap/backend/dict/demo/Sent/message-1.txt
pymap/backend/dict/demo/Sent/message-2.txt
pymap/backend/dict/demo/Trash/.readonly
pymap/backend/dict/demo/Trash/message-1.txt
pymap/backend/maildir/__init__.py
pymap/backend/maildir/flags.py
pymap/backend/maildir/io.py
pymap/backend/maildir/layout.py
pymap/backend/maildir/mailbox.py
pymap/backend/maildir/subscriptions.py
pymap/backend/maildir/uidlist.py
pymap/backend/maildir/users.py
pymap/backend/redis/__init__.py
pymap/backend/redis/background.py
pymap/backend/redis/cleanup.py
pymap/backend/redis/filter.py
pymap/backend/redis/keys.py
pymap/backend/redis/mailbox.py
pymap/backend/redis/message.py
pymap/backend/redis/scripts/__init__.py
pymap/backend/redis/scripts/cleanup.py
pymap/backend/redis/scripts/filter.py
pymap/backend/redis/scripts/mailbox.py
pymap/backend/redis/scripts/namespace.py
pymap/backend/redis/scripts/lua/cleanup_content.lua
pymap/backend/redis/scripts/lua/cleanup_mailbox.lua
pymap/backend/redis/scripts/lua/cleanup_namespace.lua
pymap-0.36.7.dist-info/METADATA
pymap-0.36.7.dist-info/WHEEL
pymap-0.36.7.dist-info/entry_points.txt
pymap-0.36.7.dist-info/licenses/LICENSE.md
pymap-0.36.7.dist-info/RECORD
