Metadata-Version: 2.3
Name: pymap
Version: 0.36.7
Summary: Lightweight, asynchronous IMAP serving in Python.
Project-URL: Homepage, https://github.com/icgood/pymap/
Project-URL: API Documentation, https://icgood.github.io/pymap/
Project-URL: Docker Image, https://github.com/icgood/pymap/pkgs/container/pymap
Author-email: Ian Good <ian@icgood.net>
License: ## The MIT License (MIT)
License-File: LICENSE.md
Classifier: Development Status :: 3 - Alpha
Classifier: Intended Audience :: Developers
Classifier: Intended Audience :: Information Technology
Classifier: License :: OSI Approved :: MIT License
Classifier: Programming Language :: Python
Classifier: Programming Language :: Python :: 3.11
Classifier: Programming Language :: Python :: 3.12
Classifier: Topic :: Communications :: Email :: Post-Office
Classifier: Topic :: Communications :: Email :: Post-Office :: IMAP
Requires-Python: ~=3.11
Requires-Dist: proxy-protocol~=0.11.1
Requires-Dist: pysasl~=1.2
Provides-Extra: admin
Requires-Dist: pymap-admin~=0.12.1; extra == 'admin'
Provides-Extra: dev
Requires-Dist: autopep8; extra == 'dev'
Requires-Dist: mypy; extra == 'dev'
Requires-Dist: pycodestyle; extra == 'dev'
Requires-Dist: pytest; extra == 'dev'
Requires-Dist: pytest-asyncio; extra == 'dev'
Requires-Dist: pytest-cov; extra == 'dev'
Requires-Dist: ruff; extra == 'dev'
Requires-Dist: types-certifi; extra == 'dev'
Requires-Dist: types-passlib; extra == 'dev'
Requires-Dist: types-protobuf; extra == 'dev'
Requires-Dist: types-redis; extra == 'dev'
Requires-Dist: types-toml; extra == 'dev'
Provides-Extra: doc
Requires-Dist: cloud-sptheme; extra == 'doc'
Requires-Dist: sphinx; extra == 'doc'
Requires-Dist: sphinx-autodoc-typehints; extra == 'doc'
Provides-Extra: macaroon
Requires-Dist: pymacaroons~=0.13.0; extra == 'macaroon'
Provides-Extra: optional
Requires-Dist: hiredis; extra == 'optional'
Requires-Dist: passlib~=1.7; extra == 'optional'
Requires-Dist: pid~=3.0; extra == 'optional'
Provides-Extra: redis
Requires-Dist: msgpack~=1.0; extra == 'redis'
Requires-Dist: redis~=4.2; extra == 'redis'
Provides-Extra: sieve
Requires-Dist: setuptools; extra == 'sieve'
Requires-Dist: sievelib~=1.2; extra == 'sieve'
Provides-Extra: swim
Requires-Dist: swim-protocol~=0.6.3; extra == 'swim'
Provides-Extra: systemd
Requires-Dist: systemd-python; extra == 'systemd'
